image_optimizer/__init__.py
image_optimizer/__main__.py
image_optimizer/errors.py
image_optimizer/optimizer.py
image_optimizer/resizer.py
image_optimizer/utils.py
image_optimizer-0.3.6.dist-info/METADATA
image_optimizer-0.3.6.dist-info/WHEEL
image_optimizer-0.3.6.dist-info/entry_points.txt
image_optimizer-0.3.6.dist-info/top_level.txt
image_optimizer-0.3.6.dist-info/RECORD
