Metadata-Version: 2.1
Name: image-optimizer
Version: 0.3.6
Summary: PIL based image optimizer
Home-page: https://github.com/Bobsans/image-optimizer
Author: Bobsans
Author-email: mr.bobsans@gmail.com
Maintainer: Bobsans
Maintainer-email: mr.bobsans@gmail.com
License: Freeware
Download-URL: https://pypi.python.org/pypi/image_optimizer
Keywords: PIL optimize image
Platform: Any
Classifier: Development Status :: 5 - Production/Stable
Classifier: Environment :: Console
Classifier: License :: Freeware
Classifier: Natural Language :: English
Classifier: Natural Language :: Russian
Classifier: Programming Language :: Python
Classifier: Programming Language :: Python :: 3
Classifier: Programming Language :: Python :: 3.3
Classifier: Programming Language :: Python :: 3.4
Classifier: Programming Language :: Python :: 3.5
Classifier: Programming Language :: Python :: 3.6
Classifier: Programming Language :: Python :: 3.7
Classifier: Programming Language :: Python :: Implementation :: PyPy
Classifier: Topic :: Multimedia :: Graphics
Classifier: Topic :: Utilities
Requires-Dist: Pillow
